fastgrpc/__init__.py
fastgrpc/applications.py
fastgrpc/dependencies.py
fastgrpc/handler.py
fastgrpc/manage.py
fastgrpc/tools.py
fastgrpc/typedef.py
fastgrpc-0.1.0.dist-info/LICENSE.md
fastgrpc-0.1.0.dist-info/WHEEL
fastgrpc-0.1.0.dist-info/METADATA
fastgrpc-0.1.0.dist-info/RECORD
